MANIFEST.in
README.md
setup.py
resttools/VERSION
resttools/__init__.py
resttools/dao.py
resttools/exceptions.py
resttools/gws.py
resttools/irws.py
resttools/ntfyws.py
resttools/nws.py
resttools/tests.py
resttools/dao_implementation/__init__.py
resttools/dao_implementation/gws.py
resttools/dao_implementation/irws.py
resttools/dao_implementation/live.py
resttools/dao_implementation/mock.py
resttools/dao_implementation/ntfyws.py
resttools/dao_implementation/nws.py
resttools/mock/__init__.py
resttools/mock/mock_http.py
resttools/mock/gws/group_sws/v2/search_member_javerage
resttools/mock/gws/group_sws/v2/search_name_2015spr-phys%2A1_stem_course
resttools/mock/gws/group_sws/v2/search_stem_u_fox_browser6
resttools/mock/gws/group_sws/v2/search_stem_u_fox_unittest
resttools/mock/gws/group_sws/v2/group/course_2015spr-phys114a.resource
resttools/mock/gws/group_sws/v2/group/u_fox_browser6.resource
resttools/mock/gws/group_sws/v2/group/u_fox_unittest.resource
resttools/mock/gws/group_sws/v2/group/course_2015spr-phys114a/README.member
resttools/mock/gws/group_sws/v2/group/course_2015spr-phys114a/member
resttools/mock/gws/group_sws/v2/group/course_2015spr-phys114a/member.http-headers
resttools/mock/gws/group_sws/v2/group/u_fox_browser6/member
resttools/mock/gws/group_sws/v2/group/u_fox_unittest/member
resttools/mock/irws/registry-dev/v2/person_uwnetid_javerage
resttools/mock/irws/registry-dev/v2/person_uwnetid_javerage_birthdate_2015-10-04
resttools/mock/irws/registry-dev/v2/person_uwnetid_wdspud867
resttools/mock/irws/registry-dev/v2/person_validid_regid_DC5C0C166A7C11D5A4AE0004AC494FFE
resttools/mock/irws/registry-dev/v2/qna_uwnetid_user1q
resttools/mock/irws/registry-dev/v2/regid_uwnetid_joeuser
resttools/mock/irws/registry-dev/v2/regid_validid_regid_FC8E9A4FD5A940ACAC6306EA7DC7D742
resttools/mock/irws/registry-dev/v2/uwnetid_validid_1_003433412_status_30
resttools/mock/irws/registry-dev/v2/uwnetid_validid_1_881001412_status_30
uw_iam_resttools.egg-info/PKG-INFO
uw_iam_resttools.egg-info/SOURCES.txt
uw_iam_resttools.egg-info/dependency_links.txt
uw_iam_resttools.egg-info/requires.txt
uw_iam_resttools.egg-info/top_level.txt