Metadata-Version: 2.1
Name: uw-iam-resttools
Version: 1.3.0
Summary: UW-IT REST library for IAM APIs
Home-page: https://github.com/UWIT-IAM/iam-resttools
Author: UW-IT Identity and Access Management
Author-email: help@uw.edu
License: Apache License, Version 2.0
Platform: UNKNOWN
